outfitai/__init__.py
outfitai/__main__.py
outfitai/cli.py
outfitai/classifier/__init__.py
outfitai/classifier/base.py
outfitai/classifier/factory.py
outfitai/classifier/gemini_classifier.py
outfitai/classifier/openai_classifier.py
outfitai/config/__init__.py
outfitai/config/settings.py
outfitai/error/__init__.py
outfitai/error/exceptions.py
outfitai/utils/__init__.py
outfitai/utils/image_processor.py
outfitai/utils/logger.py
outfitai-1.2.4.dist-info/licenses/LICENSE
outfitai-1.2.4.dist-info/METADATA
outfitai-1.2.4.dist-info/WHEEL
outfitai-1.2.4.dist-info/entry_points.txt
outfitai-1.2.4.dist-info/top_level.txt
outfitai-1.2.4.dist-info/RECORD
