Metadata-Version: 2.4
Name: outfitai
Version: 1.2.4
Summary: AI-powered clothing image classification tool.
Author: 23tae
Author-email: taehoonkim.dev@gmail.com
License: MIT
Project-URL: Source, https://github.com/23tae/outfitai
Classifier: License :: OSI Approved :: MIT License
Classifier: Programming Language :: Python :: 3
Classifier: Programming Language :: Python :: 3.9
Classifier: Programming Language :: Python :: 3.10
Classifier: Programming Language :: Python :: 3.11
Classifier: Programming Language :: Python :: 3.12
Classifier: Programming Language :: Python :: 3.13
Requires-Python: >=3.9
License-File: LICENSE
Requires-Dist: openai>=1.61.0
Requires-Dist: pillow
Requires-Dist: pydantic-settings>=2.7.0
Requires-Dist: click>=8.1.0
Requires-Dist: asyncio>=3.4.0
Requires-Dist: google-genai>=1.2.0
Requires-Dist: pydantic>=2.10.0
Dynamic: author
Dynamic: author-email
Dynamic: classifier
Dynamic: description
Dynamic: description-content-type
Dynamic: license
Dynamic: license-file
Dynamic: project-url
Dynamic: requires-dist
Dynamic: requires-python
Dynamic: summary
